MANIFEST.in
__info__.py
setup.py
./appomatic_cms_tagging.egg-info/SOURCES.txt
./appomatic_cms_tagging.egg-info/dependency_links.txt
./appomatic_cms_tagging.egg-info/requires.txt
./appomatic_cms_tagging.egg-info/top_level.txt
./appomatic_cms_tagging/templates/cms_tagging/tagged_list.html
appomatic_cms_tagging/__app__.py
appomatic_cms_tagging/__init__.py
appomatic_cms_tagging/admin.py
appomatic_cms_tagging/cms_plugins.py
appomatic_cms_tagging/models.py
appomatic_cms_tagging.egg-info/PKG-INFO
appomatic_cms_tagging.egg-info/SOURCES.txt
appomatic_cms_tagging.egg-info/dependency_links.txt
appomatic_cms_tagging.egg-info/requires.txt
appomatic_cms_tagging.egg-info/top_level.txt
appomatic_cms_tagging/migrations/0001_add_tag_field.py
appomatic_cms_tagging/migrations/0002_add_model_TaggedList.py
appomatic_cms_tagging/migrations/__init__.py
appomatic_cms_tagging/templates/__init__.py
appomatic_cms_tagging/templates/cms_tagging/__init__.py