Metadata-Version: 1.0
Name: appomatic-cms-tagging
Version: 0.0.32
Summary: Adds tagging support to django-cms
Home-page: http://github.com/redhog/appomatic
Author: RedHog (Egil Moeller)
Author-email: egil.moller@freecode.no
License: GPL
Keywords: appomatic django-tagging django-cms
Platform: UNKNOWN
